pyusb_tree/__init__.py
pyusb_tree/parser.py
pyusb_tree/py.typed
pyusb_tree/bin/UsbTreeView.exe
pyusb_tree-1.0.1.dist-info/LICENSE
pyusb_tree-1.0.1.dist-info/METADATA
pyusb_tree-1.0.1.dist-info/WHEEL
pyusb_tree-1.0.1.dist-info/top_level.txt
pyusb_tree-1.0.1.dist-info/RECORD
