Metadata-Version: 2.1
Name: pyusb-tree
Version: 1.0.1
Summary: Python package to parse USB Device Tree Viewer output to pydantic
Author-email: Pradish Bijukchhe <pradish@sandbox.com.np>
License: Copyright (c) 2018 The Python Packaging Authority
Project-URL: Homepage, https://github.com/sandbox-pokhara/pyusb-tree
Project-URL: Issues, https://github.com/sandbox-pokhara/pyusb-tree/issues
Classifier: Programming Language :: Python :: 3
Requires-Python: >=3
License-File: LICENSE
Requires-Dist: pydantic
